gocodeo_cli/__init__.py
gocodeo_cli/cli.py
gocodeo_cli/agents/__init__.py
gocodeo_cli/agents/base.py
gocodeo_cli/agents/build_agent.py
gocodeo_cli/commands/__init__.py
gocodeo_cli/commands/build.py
gocodeo_cli/services/__init__.py
gocodeo_cli/services/llm_service.py
gocodeo_cli/services/project_state.py
gocodeo_cli/templates/prompts/auth.txt
gocodeo_cli/templates/prompts/data.txt
gocodeo_cli/templates/prompts/init.txt
gocodeo_cli/templates/prompts/init_ui.txt
gocodeo_cli/templates/prompts/sql_migrations.txt
gocodeo_cli/templates/prompts/system.txt
gocodeo_cli/templates/stacks/crm.zip
gocodeo_cli/templates/stacks/e-commerce_template.zip
gocodeo_cli/templates/stacks/marketing_template.zip
gocodeo_cli/templates/stacks/sample_ui_e-commerce.zip
gocodeo_cli/tools/__init__.py
gocodeo_cli/tools/build_tools.py
gocodeo_cli/tools/env_tools.py
gocodeo_cli/tools/npm_tools.py
gocodeo_cli/tools/sql_tools.py
gocodeo_cli/utils/__init__.py
gocodeo_cli/utils/config.py
gocodeo_cli/utils/progress.py
aib_cli-0.5.dist-info/METADATA
aib_cli-0.5.dist-info/WHEEL
aib_cli-0.5.dist-info/entry_points.txt
aib_cli-0.5.dist-info/licenses/LICENSE
aib_cli-0.5.dist-info/RECORD
