Metadata-Version: 2.4
Name: aib-cli
Version: 0.5
Summary: AI-powered CLI tool for build your full-stack  applications in minutes
Author-email: GoCodeo <support@gocodeo.com>
License-File: LICENSE
Keywords: AI,Agent,CLI,Code Generation,Full-Stack
Requires-Python: >=3.10
Requires-Dist: anthropic>=0.18.1
Requires-Dist: google-generativeai>=0.5.0
Requires-Dist: json-repair>=0.30.0
Requires-Dist: openai>=1.12.0
Requires-Dist: python-dotenv>=1.0.0
Requires-Dist: rich>=13.7.0
Requires-Dist: typer>=0.9.0
